setup.py
cmds/__init__.py
cmds/setupB.py
cmds.py.egg-info/PKG-INFO
cmds.py.egg-info/SOURCES.txt
cmds.py.egg-info/dependency_links.txt
cmds.py.egg-info/top_level.txt