Metadata-Version: 2.1
Name: cmds.py
Version: 0.159
Summary: My CMD 模組
Home-page: UNKNOWN
License: LGPL
Platform: UNKNOWN
